{
    "all_public_dependent_repos": [
        {
            "name": "C-gyorfi/govuk-front-end-rails-app",
            "stars": 0,
            "img": "https://avatars.githubusercontent.com/u/22743709?s=40&v=4",
            "owner": "C-gyorfi",
            "repo_name": "govuk-front-end-rails-app"
        },
        {
            "name": "Chillclamp/rubyOnRails",
            "stars": 0,
            "img": "https://avatars.githubusercontent.com/u/133668746?s=40&v=4",
            "owner": "Chillclamp",
            "repo_name": "rubyOnRails"
        },
        {
            "name": "DEFRA/flood-risk-back-office",
            "stars": 2,
            "img": "https://avatars.githubusercontent.com/u/5528822?s=40&v=4",
            "owner": "DEFRA",
            "repo_name": "flood-risk-back-office"
        },
        {
            "name": "DEFRA/flood-risk-engine",
            "stars": 3,
            "img": "https://avatars.githubusercontent.com/u/5528822?s=40&v=4",
            "owner": "DEFRA",
            "repo_name": "flood-risk-engine"
        },
        {
            "name": "DEFRA/flood-risk-front-office",
            "stars": 2,
            "img": "https://avatars.githubusercontent.com/u/5528822?s=40&v=4",
            "owner": "DEFRA",
            "repo_name": "flood-risk-front-office"
        },
        {
            "name": "DEFRA/pafs-admin",
            "stars": 0,
            "img": "https://avatars.githubusercontent.com/u/5528822?s=40&v=4",
            "owner": "DEFRA",
            "repo_name": "pafs-admin"
        },
        {
            "name": "DEFRA/pafs-user",
            "stars": 2,
            "img": "https://avatars.githubusercontent.com/u/5528822?s=40&v=4",
            "owner": "DEFRA",
            "repo_name": "pafs-user"
        },
        {
            "name": "DEFRA/pafs_core",
            "stars": 0,
            "img": "https://avatars.githubusercontent.com/u/5528822?s=40&v=4",
            "owner": "DEFRA",
            "repo_name": "pafs_core"
        },
        {
            "name": "DEFRA/waste-carriers-back-office",
            "stars": 0,
            "img": "https://avatars.githubusercontent.com/u/5528822?s=40&v=4",
            "owner": "DEFRA",
            "repo_name": "waste-carriers-back-office"
        },
        {
            "name": "DEFRA/waste-carriers-engine",
            "stars": 0,
            "img": "https://avatars.githubusercontent.com/u/5528822?s=40&v=4",
            "owner": "DEFRA",
            "repo_name": "waste-carriers-engine"
        },
        {
            "name": "DEFRA/waste-carriers-front-office",
            "stars": 0,
            "img": "https://avatars.githubusercontent.com/u/5528822?s=40&v=4",
            "owner": "DEFRA",
            "repo_name": "waste-carriers-front-office"
        },
        {
            "name": "DFE-Digital/access-your-teaching-profile",
            "stars": 0,
            "img": "https://avatars.githubusercontent.com/u/30029772?s=40&v=4",
            "owner": "DFE-Digital",
            "repo_name": "access-your-teaching-profile"
        },
        {
            "name": "DFE-Digital/access-your-teaching-qualifications",
            "stars": 1,
            "img": "https://avatars.githubusercontent.com/u/30029772?s=40&v=4",
            "owner": "DFE-Digital",
            "repo_name": "access-your-teaching-qualifications"
        },
        {
            "name": "DFE-Digital/apply-for-qualified-teacher-status",
            "stars": 6,
            "img": "https://avatars.githubusercontent.com/u/30029772?s=40&v=4",
            "owner": "DFE-Digital",
            "repo_name": "apply-for-qualified-teacher-status"
        },
        {
            "name": "DFE-Digital/apply-for-teacher-training",
            "stars": 37,
            "img": "https://avatars.githubusercontent.com/u/30029772?s=40&v=4",
            "owner": "DFE-Digital",
            "repo_name": "apply-for-teacher-training"
        },
        {
            "name": "DFE-Digital/bat-ops-dashboard",
            "stars": 0,
            "img": "https://avatars.githubusercontent.com/u/30029772?s=40&v=4",
            "owner": "DFE-Digital",
            "repo_name": "bat-ops-dashboard"
        },
        {
            "name": "DFE-Digital/buy-for-your-school",
            "stars": 5,
            "img": "https://avatars.githubusercontent.com/u/30029772?s=40&v=4",
            "owner": "DFE-Digital",
            "repo_name": "buy-for-your-school"
        },
        {
            "name": "DFE-Digital/check-childrens-barred-list",
            "stars": 2,
            "img": "https://avatars.githubusercontent.com/u/30029772?s=40&v=4",
            "owner": "DFE-Digital",
            "repo_name": "check-childrens-barred-list"
        },
        {
            "name": "DFE-Digital/childrens-social-care-placement",
            "stars": 0,
            "img": "https://avatars.githubusercontent.com/u/30029772?s=40&v=4",
            "owner": "DFE-Digital",
            "repo_name": "childrens-social-care-placement"
        },
        {
            "name": "DFE-Digital/claim-additional-payments-for-teaching",
            "stars": 14,
            "img": "https://avatars.githubusercontent.com/u/30029772?s=40&v=4",
            "owner": "DFE-Digital",
            "repo_name": "claim-additional-payments-for-teaching"
        },
        {
            "name": "DFE-Digital/csc-swr-prototype",
            "stars": 0,
            "img": "https://avatars.githubusercontent.com/u/30029772?s=40&v=4",
            "owner": "DFE-Digital",
            "repo_name": "csc-swr-prototype"
        },
        {
            "name": "DFE-Digital/curriculum-materials",
            "stars": 2,
            "img": "https://avatars.githubusercontent.com/u/30029772?s=40&v=4",
            "owner": "DFE-Digital",
            "repo_name": "curriculum-materials"
        },
        {
            "name": "DFE-Digital/data-allowances-prototype",
            "stars": 0,
            "img": "https://avatars.githubusercontent.com/u/30029772?s=40&v=4",
            "owner": "DFE-Digital",
            "repo_name": "data-allowances-prototype"
        },
        {
            "name": "DFE-Digital/dfe-complete-conversions-transfers-and-changes",
            "stars": 2,
            "img": "https://avatars.githubusercontent.com/u/30029772?s=40&v=4",
            "owner": "DFE-Digital",
            "repo_name": "dfe-complete-conversions-transfers-and-changes"
        },
        {
            "name": "DFE-Digital/early-careers-framework",
            "stars": 8,
            "img": "https://avatars.githubusercontent.com/u/30029772?s=40&v=4",
            "owner": "DFE-Digital",
            "repo_name": "early-careers-framework"
        },
        {
            "name": "DFE-Digital/early-years-foundation-recovery",
            "stars": 5,
            "img": "https://avatars.githubusercontent.com/u/30029772?s=40&v=4",
            "owner": "DFE-Digital",
            "repo_name": "early-years-foundation-recovery"
        },
        {
            "name": "DFE-Digital/early-years-foundation-reform",
            "stars": 6,
            "img": "https://avatars.githubusercontent.com/u/30029772?s=40&v=4",
            "owner": "DFE-Digital",
            "repo_name": "early-years-foundation-reform"
        },
        {
            "name": "DFE-Digital/find-a-buying-solution",
            "stars": 0,
            "img": "https://avatars.githubusercontent.com/u/30029772?s=40&v=4",
            "owner": "DFE-Digital",
            "repo_name": "find-a-buying-solution"
        },
        {
            "name": "DFE-Digital/find-a-lost-trn",
            "stars": 4,
            "img": "https://avatars.githubusercontent.com/u/30029772?s=40&v=4",
            "owner": "DFE-Digital",
            "repo_name": "find-a-lost-trn"
        },
        {
            "name": "DFE-Digital/find-teacher-training",
            "stars": 6,
            "img": "https://avatars.githubusercontent.com/u/30029772?s=40&v=4",
            "owner": "DFE-Digital",
            "repo_name": "find-teacher-training"
        },
        {
            "name": "DFE-Digital/formbuilder-demo",
            "stars": 3,
            "img": "https://avatars.githubusercontent.com/u/30029772?s=40&v=4",
            "owner": "DFE-Digital",
            "repo_name": "formbuilder-demo"
        },
        {
            "name": "DFE-Digital/get-a-teacher-relocation-payment",
            "stars": 0,
            "img": "https://avatars.githubusercontent.com/u/30029772?s=40&v=4",
            "owner": "DFE-Digital",
            "repo_name": "get-a-teacher-relocation-payment"
        },
        {
            "name": "DFE-Digital/get-help-with-remote-education",
            "stars": 1,
            "img": "https://avatars.githubusercontent.com/u/30029772?s=40&v=4",
            "owner": "DFE-Digital",
            "repo_name": "get-help-with-remote-education"
        },
        {
            "name": "DFE-Digital/get-into-teaching-app",
            "stars": 15,
            "img": "https://avatars.githubusercontent.com/u/30029772?s=40&v=4",
            "owner": "DFE-Digital",
            "repo_name": "get-into-teaching-app"
        },
        {
            "name": "DFE-Digital/govuk-rails-boilerplate",
            "stars": 25,
            "img": "https://avatars.githubusercontent.com/u/30029772?s=40&v=4",
            "owner": "DFE-Digital",
            "repo_name": "govuk-rails-boilerplate"
        },
        {
            "name": "DFE-Digital/govuk-wizardry",
            "stars": 5,
            "img": "https://avatars.githubusercontent.com/u/30029772?s=40&v=4",
            "owner": "DFE-Digital",
            "repo_name": "govuk-wizardry"
        },
        {
            "name": "DFE-Digital/govuk_feature_flags",
            "stars": 4,
            "img": "https://avatars.githubusercontent.com/u/30029772?s=40&v=4",
            "owner": "DFE-Digital",
            "repo_name": "govuk_feature_flags"
        },
        {
            "name": "DFE-Digital/help-for-early-years-providers",
            "stars": 0,
            "img": "https://avatars.githubusercontent.com/u/30029772?s=40&v=4",
            "owner": "DFE-Digital",
            "repo_name": "help-for-early-years-providers"
        },
        {
            "name": "DFE-Digital/itt-mentor-services",
            "stars": 1,
            "img": "https://avatars.githubusercontent.com/u/30029772?s=40&v=4",
            "owner": "DFE-Digital",
            "repo_name": "itt-mentor-services"
        },
        {
            "name": "DFE-Digital/national-professional-qualification",
            "stars": 0,
            "img": "https://avatars.githubusercontent.com/u/30029772?s=40&v=4",
            "owner": "DFE-Digital",
            "repo_name": "national-professional-qualification"
        },
        {
            "name": "DFE-Digital/npq-registration",
            "stars": 5,
            "img": "https://avatars.githubusercontent.com/u/30029772?s=40&v=4",
            "owner": "DFE-Digital",
            "repo_name": "npq-registration"
        },
        {
            "name": "DFE-Digital/publish-teacher-training",
            "stars": 9,
            "img": "https://avatars.githubusercontent.com/u/30029772?s=40&v=4",
            "owner": "DFE-Digital",
            "repo_name": "publish-teacher-training"
        },
        {
            "name": "DFE-Digital/publish-teacher-training-2022",
            "stars": 5,
            "img": "https://avatars.githubusercontent.com/u/30029772?s=40&v=4",
            "owner": "DFE-Digital",
            "repo_name": "publish-teacher-training-2022"
        },
        {
            "name": "DFE-Digital/rails-7-boilerplate",
            "stars": 1,
            "img": "https://avatars.githubusercontent.com/u/30029772?s=40&v=4",
            "owner": "DFE-Digital",
            "repo_name": "rails-7-boilerplate"
        },
        {
            "name": "DFE-Digital/refer-serious-misconduct",
            "stars": 3,
            "img": "https://avatars.githubusercontent.com/u/30029772?s=40&v=4",
            "owner": "DFE-Digital",
            "repo_name": "refer-serious-misconduct"
        },
        {
            "name": "DFE-Digital/register-early-career-teachers-public",
            "stars": 1,
            "img": "https://avatars.githubusercontent.com/u/30029772?s=40&v=4",
            "owner": "DFE-Digital",
            "repo_name": "register-early-career-teachers-public"
        },
        {
            "name": "DFE-Digital/register-trainee-teachers",
            "stars": 11,
            "img": "https://avatars.githubusercontent.com/u/30029772?s=40&v=4",
            "owner": "DFE-Digital",
            "repo_name": "register-trainee-teachers"
        },
        {
            "name": "DFE-Digital/ruby-technical-test",
            "stars": 0,
            "img": "https://avatars.githubusercontent.com/u/30029772?s=40&v=4",
            "owner": "DFE-Digital",
            "repo_name": "ruby-technical-test"
        },
        {
            "name": "DFE-Digital/schools-experience",
            "stars": 9,
            "img": "https://avatars.githubusercontent.com/u/30029772?s=40&v=4",
            "owner": "DFE-Digital",
            "repo_name": "schools-experience"
        },
        {
            "name": "DFE-Digital/teacher-pay-calculator",
            "stars": 0,
            "img": "https://avatars.githubusercontent.com/u/30029772?s=40&v=4",
            "owner": "DFE-Digital",
            "repo_name": "teacher-pay-calculator"
        },
        {
            "name": "DFE-Digital/teaching-school-hub-finder",
            "stars": 1,
            "img": "https://avatars.githubusercontent.com/u/30029772?s=40&v=4",
            "owner": "DFE-Digital",
            "repo_name": "teaching-school-hub-finder"
        },
        {
            "name": "DFE-Digital/teaching-vacancies",
            "stars": 23,
            "img": "https://avatars.githubusercontent.com/u/30029772?s=40&v=4",
            "owner": "DFE-Digital",
            "repo_name": "teaching-vacancies"
        },
        {
            "name": "FayeGoodworth/buy-for-your-school",
            "stars": 0,
            "img": "https://avatars.githubusercontent.com/u/62703351?s=40&v=4",
            "owner": "FayeGoodworth",
            "repo_name": "buy-for-your-school"
        },
        {
            "name": "GovWifi/govwifi-admin",
            "stars": 8,
            "img": "https://avatars.githubusercontent.com/u/178180623?s=40&v=4",
            "owner": "GovWifi",
            "repo_name": "govwifi-admin"
        },
        {
            "name": "Larisa-Romero/registro-docente",
            "stars": 0,
            "img": "https://avatars.githubusercontent.com/u/119458932?s=40&v=4",
            "owner": "Larisa-Romero",
            "repo_name": "registro-docente"
        },
        {
            "name": "Lloyd-K/get-help-with-tech",
            "stars": 0,
            "img": "https://avatars.githubusercontent.com/u/68383886?s=40&v=4",
            "owner": "Lloyd-K",
            "repo_name": "get-help-with-tech"
        },
        {
            "name": "OfficeForProductSafetyAndStandards/cosmetic-product-notifications",
            "stars": 14,
            "img": "https://avatars.githubusercontent.com/u/110820998?s=40&v=4",
            "owner": "OfficeForProductSafetyAndStandards",
            "repo_name": "cosmetic-product-notifications"
        },
        {
            "name": "OfficeForProductSafetyAndStandards/product-safety-database",
            "stars": 6,
            "img": "https://avatars.githubusercontent.com/u/110820998?s=40&v=4",
            "owner": "OfficeForProductSafetyAndStandards",
            "repo_name": "product-safety-database"
        },
        {
            "name": "UKGovernmentBEIS/beis-report-official-development-assistance",
            "stars": 5,
            "img": "https://avatars.githubusercontent.com/u/19221939?s=40&v=4",
            "owner": "UKGovernmentBEIS",
            "repo_name": "beis-report-official-development-assistance"
        },
        {
            "name": "alphagov/forms-admin",
            "stars": 17,
            "img": "https://avatars.githubusercontent.com/u/596977?s=40&v=4",
            "owner": "alphagov",
            "repo_name": "forms-admin"
        },
        {
            "name": "alphagov/forms-product-page",
            "stars": 10,
            "img": "https://avatars.githubusercontent.com/u/596977?s=40&v=4",
            "owner": "alphagov",
            "repo_name": "forms-product-page"
        },
        {
            "name": "alphagov/forms-runner",
            "stars": 9,
            "img": "https://avatars.githubusercontent.com/u/596977?s=40&v=4",
            "owner": "alphagov",
            "repo_name": "forms-runner"
        },
        {
            "name": "boost-entropy-ruby/govwifi-admin",
            "stars": 0,
            "img": "https://avatars.githubusercontent.com/u/83460344?s=40&v=4",
            "owner": "boost-entropy-ruby",
            "repo_name": "govwifi-admin"
        },
        {
            "name": "cabinetoffice/fb-editor",
            "stars": 0,
            "img": "https://avatars.githubusercontent.com/u/5442909?s=40&v=4",
            "owner": "cabinetoffice",
            "repo_name": "fb-editor"
        },
        {
            "name": "cabinetoffice/fb-metadata-api",
            "stars": 0,
            "img": "https://avatars.githubusercontent.com/u/5442909?s=40&v=4",
            "owner": "cabinetoffice",
            "repo_name": "fb-metadata-api"
        },
        {
            "name": "cabinetoffice/fb-metadata-presenter",
            "stars": 0,
            "img": "https://avatars.githubusercontent.com/u/5442909?s=40&v=4",
            "owner": "cabinetoffice",
            "repo_name": "fb-metadata-presenter"
        },
        {
            "name": "cabinetoffice/fb-runner",
            "stars": 0,
            "img": "https://avatars.githubusercontent.com/u/5442909?s=40&v=4",
            "owner": "cabinetoffice",
            "repo_name": "fb-runner"
        },
        {
            "name": "cadmiumcat/forms-runner",
            "stars": 0,
            "img": "https://avatars.githubusercontent.com/u/52242161?s=40&v=4",
            "owner": "cadmiumcat",
            "repo_name": "forms-runner"
        },
        {
            "name": "chris-groves/GDS-tasks",
            "stars": 0,
            "img": "https://avatars.githubusercontent.com/u/46629384?s=40&v=4",
            "owner": "chris-groves",
            "repo_name": "GDS-tasks"
        },
        {
            "name": "chris-groves/rock-paper-scissors",
            "stars": 0,
            "img": "https://avatars.githubusercontent.com/u/46629384?s=40&v=4",
            "owner": "chris-groves",
            "repo_name": "rock-paper-scissors"
        },
        {
            "name": "cmagovuk/oim-report-an-issue-app",
            "stars": 0,
            "img": "https://avatars.githubusercontent.com/u/49915532?s=40&v=4",
            "owner": "cmagovuk",
            "repo_name": "oim-report-an-issue-app"
        },
        {
            "name": "cmagovuk/public-access-gateway-app",
            "stars": 1,
            "img": "https://avatars.githubusercontent.com/u/49915532?s=40&v=4",
            "owner": "cmagovuk",
            "repo_name": "public-access-gateway-app"
        },
        {
            "name": "cmagovuk/sau-pa-portal",
            "stars": 0,
            "img": "https://avatars.githubusercontent.com/u/49915532?s=40&v=4",
            "owner": "cmagovuk",
            "repo_name": "sau-pa-portal"
        },
        {
            "name": "cmagovuk/whistleblower",
            "stars": 0,
            "img": "https://avatars.githubusercontent.com/u/49915532?s=40&v=4",
            "owner": "cmagovuk",
            "repo_name": "whistleblower"
        },
        {
            "name": "co-cddo/dea-register-frontend",
            "stars": 0,
            "img": "https://avatars.githubusercontent.com/u/94975489?s=40&v=4",
            "owner": "co-cddo",
            "repo_name": "dea-register-frontend"
        },
        {
            "name": "co-cddo/dm-client-demo",
            "stars": 0,
            "img": "https://avatars.githubusercontent.com/u/94975489?s=40&v=4",
            "owner": "co-cddo",
            "repo_name": "dm-client-demo"
        },
        {
            "name": "co-cddo/esda-builder",
            "stars": 0,
            "img": "https://avatars.githubusercontent.com/u/94975489?s=40&v=4",
            "owner": "co-cddo",
            "repo_name": "esda-builder"
        },
        {
            "name": "communitiesuk/submit-social-housing-lettings-and-sales-data",
            "stars": 6,
            "img": "https://avatars.githubusercontent.com/u/12797589?s=40&v=4",
            "owner": "communitiesuk",
            "repo_name": "submit-social-housing-lettings-and-sales-data"
        },
        {
            "name": "communitiesuk/ukraine-sponsor-resettlement",
            "stars": 6,
            "img": "https://avatars.githubusercontent.com/u/12797589?s=40&v=4",
            "owner": "communitiesuk",
            "repo_name": "ukraine-sponsor-resettlement"
        },
        {
            "name": "design-history/design-history",
            "stars": 10,
            "img": "https://avatars.githubusercontent.com/u/86117238?s=40&v=4",
            "owner": "design-history",
            "repo_name": "design-history"
        },
        {
            "name": "dsp-testing/apply-for-teacher-training",
            "stars": 0,
            "img": "https://avatars.githubusercontent.com/u/30846345?s=40&v=4",
            "owner": "dsp-testing",
            "repo_name": "apply-for-teacher-training"
        },
        {
            "name": "dxw/dfsseta-apply-for-landing-ruby",
            "stars": 1,
            "img": "https://avatars.githubusercontent.com/u/27897?s=40&v=4",
            "owner": "dxw",
            "repo_name": "dfsseta-apply-for-landing-ruby"
        },
        {
            "name": "ebrett/rails7example",
            "stars": 1,
            "img": "https://avatars.githubusercontent.com/u/6605?s=40&v=4",
            "owner": "ebrett",
            "repo_name": "rails7example"
        },
        {
            "name": "fumimowdan/irp_policy",
            "stars": 0,
            "img": "https://avatars.githubusercontent.com/u/139925286?s=40&v=4",
            "owner": "fumimowdan",
            "repo_name": "irp_policy"
        },
        {
            "name": "gpeng/dfe-code-test",
            "stars": 0,
            "img": "https://avatars.githubusercontent.com/u/5216?s=40&v=4",
            "owner": "gpeng",
            "repo_name": "dfe-code-test"
        },
        {
            "name": "graphia/wizardry-demo",
            "stars": 0,
            "img": "https://avatars.githubusercontent.com/u/25978684?s=40&v=4",
            "owner": "graphia",
            "repo_name": "wizardry-demo"
        },
        {
            "name": "graphia/wizardry-sample-app",
            "stars": 0,
            "img": "https://avatars.githubusercontent.com/u/25978684?s=40&v=4",
            "owner": "graphia",
            "repo_name": "wizardry-sample-app"
        },
        {
            "name": "hmcts/c100-application",
            "stars": 0,
            "img": "https://avatars.githubusercontent.com/u/22817111?s=40&v=4",
            "owner": "hmcts",
            "repo_name": "c100-application"
        },
        {
            "name": "hmcts/et-pet-et1",
            "stars": 9,
            "img": "https://avatars.githubusercontent.com/u/22817111?s=40&v=4",
            "owner": "hmcts",
            "repo_name": "et-pet-et1"
        },
        {
            "name": "hmcts/et-pet-et3",
            "stars": 2,
            "img": "https://avatars.githubusercontent.com/u/22817111?s=40&v=4",
            "owner": "hmcts",
            "repo_name": "et-pet-et3"
        },
        {
            "name": "hmcts/et_gds_design_system",
            "stars": 0,
            "img": "https://avatars.githubusercontent.com/u/22817111?s=40&v=4",
            "owner": "hmcts",
            "repo_name": "et_gds_design_system"
        },
        {
            "name": "hmcts/tax-tribunals-datacapture",
            "stars": 0,
            "img": "https://avatars.githubusercontent.com/u/22817111?s=40&v=4",
            "owner": "hmcts",
            "repo_name": "tax-tribunals-datacapture"
        },
        {
            "name": "jrmhaig/govuk_formbuilder_test",
            "stars": 0,
            "img": "https://avatars.githubusercontent.com/u/4415912?s=40&v=4",
            "owner": "jrmhaig",
            "repo_name": "govuk_formbuilder_test"
        },
        {
            "name": "katalyst/govuk-formbuilder",
            "stars": 3,
            "img": "https://avatars.githubusercontent.com/u/15221?s=40&v=4",
            "owner": "katalyst",
            "repo_name": "govuk-formbuilder"
        },
        {
            "name": "katalyst/koi",
            "stars": 9,
            "img": "https://avatars.githubusercontent.com/u/15221?s=40&v=4",
            "owner": "katalyst",
            "repo_name": "koi"
        },
        {
            "name": "ministryofjustice/Claim-for-Crown-Court-Defence",
            "stars": 25,
            "img": "https://avatars.githubusercontent.com/u/2203574?s=40&v=4",
            "owner": "ministryofjustice",
            "repo_name": "Claim-for-Crown-Court-Defence"
        },
        {
            "name": "ministryofjustice/c100-application",
            "stars": 0,
            "img": "https://avatars.githubusercontent.com/u/2203574?s=40&v=4",
            "owner": "ministryofjustice",
            "repo_name": "c100-application"
        },
        {
            "name": "ministryofjustice/cdpt-deploys-dashboard",
            "stars": 0,
            "img": "https://avatars.githubusercontent.com/u/2203574?s=40&v=4",
            "owner": "ministryofjustice",
            "repo_name": "cdpt-deploys-dashboard"
        },
        {
            "name": "ministryofjustice/correspondence_tool_public",
            "stars": 3,
            "img": "https://avatars.githubusercontent.com/u/2203574?s=40&v=4",
            "owner": "ministryofjustice",
            "repo_name": "correspondence_tool_public"
        },
        {
            "name": "ministryofjustice/disclosure-checker",
            "stars": 0,
            "img": "https://avatars.githubusercontent.com/u/2203574?s=40&v=4",
            "owner": "ministryofjustice",
            "repo_name": "disclosure-checker"
        },
        {
            "name": "ministryofjustice/fb-editor",
            "stars": 0,
            "img": "https://avatars.githubusercontent.com/u/2203574?s=40&v=4",
            "owner": "ministryofjustice",
            "repo_name": "fb-editor"
        },
        {
            "name": "ministryofjustice/fb-metadata-api",
            "stars": 0,
            "img": "https://avatars.githubusercontent.com/u/2203574?s=40&v=4",
            "owner": "ministryofjustice",
            "repo_name": "fb-metadata-api"
        },
        {
            "name": "ministryofjustice/fb-metadata-presenter",
            "stars": 1,
            "img": "https://avatars.githubusercontent.com/u/2203574?s=40&v=4",
            "owner": "ministryofjustice",
            "repo_name": "fb-metadata-presenter"
        },
        {
            "name": "ministryofjustice/fb-runner",
            "stars": 1,
            "img": "https://avatars.githubusercontent.com/u/2203574?s=40&v=4",
            "owner": "ministryofjustice",
            "repo_name": "fb-runner"
        },
        {
            "name": "ministryofjustice/find-unclaimed-court-money",
            "stars": 0,
            "img": "https://avatars.githubusercontent.com/u/2203574?s=40&v=4",
            "owner": "ministryofjustice",
            "repo_name": "find-unclaimed-court-money"
        },
        {
            "name": "ministryofjustice/help-with-child-arrangements",
            "stars": 0,
            "img": "https://avatars.githubusercontent.com/u/2203574?s=40&v=4",
            "owner": "ministryofjustice",
            "repo_name": "help-with-child-arrangements"
        },
        {
            "name": "ministryofjustice/laa-apply-for-criminal-legal-aid",
            "stars": 4,
            "img": "https://avatars.githubusercontent.com/u/2203574?s=40&v=4",
            "owner": "ministryofjustice",
            "repo_name": "laa-apply-for-criminal-legal-aid"
        },
        {
            "name": "ministryofjustice/laa-apply-for-legal-aid",
            "stars": 17,
            "img": "https://avatars.githubusercontent.com/u/2203574?s=40&v=4",
            "owner": "ministryofjustice",
            "repo_name": "laa-apply-for-legal-aid"
        },
        {
            "name": "ministryofjustice/laa-assess-crime-forms",
            "stars": 0,
            "img": "https://avatars.githubusercontent.com/u/2203574?s=40&v=4",
            "owner": "ministryofjustice",
            "repo_name": "laa-assess-crime-forms"
        },
        {
            "name": "ministryofjustice/laa-assure-hmrc-data",
            "stars": 1,
            "img": "https://avatars.githubusercontent.com/u/2203574?s=40&v=4",
            "owner": "ministryofjustice",
            "repo_name": "laa-assure-hmrc-data"
        },
        {
            "name": "ministryofjustice/laa-check-client-qualifies",
            "stars": 5,
            "img": "https://avatars.githubusercontent.com/u/2203574?s=40&v=4",
            "owner": "ministryofjustice",
            "repo_name": "laa-check-client-qualifies"
        },
        {
            "name": "ministryofjustice/laa-court-data-ui",
            "stars": 7,
            "img": "https://avatars.githubusercontent.com/u/2203574?s=40&v=4",
            "owner": "ministryofjustice",
            "repo_name": "laa-court-data-ui"
        },
        {
            "name": "ministryofjustice/laa-fee-calculator-user-interface",
            "stars": 2,
            "img": "https://avatars.githubusercontent.com/u/2203574?s=40&v=4",
            "owner": "ministryofjustice",
            "repo_name": "laa-fee-calculator-user-interface"
        },
        {
            "name": "ministryofjustice/laa-review-criminal-legal-aid",
            "stars": 3,
            "img": "https://avatars.githubusercontent.com/u/2203574?s=40&v=4",
            "owner": "ministryofjustice",
            "repo_name": "laa-review-criminal-legal-aid"
        },
        {
            "name": "ministryofjustice/laa-submit-crime-forms",
            "stars": 2,
            "img": "https://avatars.githubusercontent.com/u/2203574?s=40&v=4",
            "owner": "ministryofjustice",
            "repo_name": "laa-submit-crime-forms"
        },
        {
            "name": "ministryofjustice/offender-management-allocation-manager",
            "stars": 7,
            "img": "https://avatars.githubusercontent.com/u/2203574?s=40&v=4",
            "owner": "ministryofjustice",
            "repo_name": "offender-management-allocation-manager"
        },
        {
            "name": "ministryofjustice/request-personal-information",
            "stars": 0,
            "img": "https://avatars.githubusercontent.com/u/2203574?s=40&v=4",
            "owner": "ministryofjustice",
            "repo_name": "request-personal-information"
        },
        {
            "name": "ministryofjustice/tax-tribunals-datacapture",
            "stars": 3,
            "img": "https://avatars.githubusercontent.com/u/2203574?s=40&v=4",
            "owner": "ministryofjustice",
            "repo_name": "tax-tribunals-datacapture"
        },
        {
            "name": "moda-gov-tw/alphagov.forms-admin",
            "stars": 3,
            "img": "https://avatars.githubusercontent.com/u/107838243?s=40&v=4",
            "owner": "moda-gov-tw",
            "repo_name": "alphagov.forms-admin"
        },
        {
            "name": "moda-gov-tw/alphagov.forms-runner",
            "stars": 1,
            "img": "https://avatars.githubusercontent.com/u/107838243?s=40&v=4",
            "owner": "moda-gov-tw",
            "repo_name": "alphagov.forms-runner"
        },
        {
            "name": "nareshdevasani/all_ruby_deps",
            "stars": 0,
            "img": "https://avatars.githubusercontent.com/u/22427191?s=40&v=4",
            "owner": "nareshdevasani",
            "repo_name": "all_ruby_deps"
        },
        {
            "name": "nhsuk/manage-vaccinations-in-schools",
            "stars": 8,
            "img": "https://avatars.githubusercontent.com/u/18658529?s=40&v=4",
            "owner": "nhsuk",
            "repo_name": "manage-vaccinations-in-schools"
        },
        {
            "name": "quietsoph/vocab-builder-app",
            "stars": 1,
            "img": "https://avatars.githubusercontent.com/u/101964205?s=40&v=4",
            "owner": "quietsoph",
            "repo_name": "vocab-builder-app"
        },
        {
            "name": "rowlando/apply-for-la",
            "stars": 0,
            "img": "https://avatars.githubusercontent.com/u/89347?s=40&v=4",
            "owner": "rowlando",
            "repo_name": "apply-for-la"
        },
        {
            "name": "stellenberger/rails_multi_step",
            "stars": 1,
            "img": "https://avatars.githubusercontent.com/u/53180713?s=40&v=4",
            "owner": "stellenberger",
            "repo_name": "rails_multi_step"
        },
        {
            "name": "trade-tariff/trade-tariff-admin",
            "stars": 1,
            "img": "https://avatars.githubusercontent.com/u/79591050?s=40&v=4",
            "owner": "trade-tariff",
            "repo_name": "trade-tariff-admin"
        },
        {
            "name": "trade-tariff/trade-tariff-duty-calculator",
            "stars": 2,
            "img": "https://avatars.githubusercontent.com/u/79591050?s=40&v=4",
            "owner": "trade-tariff",
            "repo_name": "trade-tariff-duty-calculator"
        },
        {
            "name": "trade-tariff/trade-tariff-frontend",
            "stars": 2,
            "img": "https://avatars.githubusercontent.com/u/79591050?s=40&v=4",
            "owner": "trade-tariff",
            "repo_name": "trade-tariff-frontend"
        },
        {
            "name": "tvararu/govuk-mockup-kit",
            "stars": 1,
            "img": "https://avatars.githubusercontent.com/u/1650875?s=40&v=4",
            "owner": "tvararu",
            "repo_name": "govuk-mockup-kit"
        },
        {
            "name": "tvararu/ravn",
            "stars": 0,
            "img": "https://avatars.githubusercontent.com/u/1650875?s=40&v=4",
            "owner": "tvararu",
            "repo_name": "ravn"
        },
        {
            "name": "unboxed/bops",
            "stars": 12,
            "img": "https://avatars.githubusercontent.com/u/47633?s=40&v=4",
            "owner": "unboxed",
            "repo_name": "bops"
        },
        {
            "name": "unboxed/bops-applicants",
            "stars": 1,
            "img": "https://avatars.githubusercontent.com/u/47633?s=40&v=4",
            "owner": "unboxed",
            "repo_name": "bops-applicants"
        },
        {
            "name": "your/status-dashboard",
            "stars": 0,
            "img": "https://avatars.githubusercontent.com/u/9043263?s=40&v=4",
            "owner": "your",
            "repo_name": "status-dashboard"
        }
    ],
    "total_dependents_number": 133,
    "public_dependents_number": 133,
    "private_dependents_number": -133,
    "public_dependents_stars": 123,
    "badges": {
        "total_doc_url": "[![Generated by github-dependents-info](https://img.shields.io/static/v1?label=Used%20by&message=133&color=informational&logo=slickpic)](https://github.com/nvuillam/github-dependents-info)",
        "total": "[![Generated by github-dependents-info](https://img.shields.io/static/v1?label=Used%20by&message=133&color=informational&logo=slickpic)](https://github.com/x-govuk/govuk-form-builder/network/dependents)",
        "public": "[![Generated by github-dependents-info](https://img.shields.io/static/v1?label=Used%20by%20(public)&message=133&color=informational&logo=slickpic)](https://github.com/x-govuk/govuk-form-builder/network/dependents)",
        "private": "[![Generated by github-dependents-info](https://img.shields.io/static/v1?label=Used%20by%20(private)&message=-133&color=informational&logo=slickpic)](https://github.com/x-govuk/govuk-form-builder/network/dependents)",
        "stars": "[![Generated by github-dependents-info](https://img.shields.io/static/v1?label=Used%20by%20(stars)&message=123&color=informational&logo=slickpic)](https://github.com/x-govuk/govuk-form-builder/network/dependents)"
    },
    "packages": [
        [
            {
                "id": null,
                "name": "x-govuk/govuk-form-builder",
                "url": "https://github.com/x-govuk/govuk-form-builder/network/dependents",
                "public_dependent_stars": 123,
                "public_dependents": [
                    {
                        "name": "C-gyorfi/govuk-front-end-rails-app",
                        "stars": 0,
                        "img": "https://avatars.githubusercontent.com/u/22743709?s=40&v=4",
                        "owner": "C-gyorfi",
                        "repo_name": "govuk-front-end-rails-app"
                    },
                    {
                        "name": "Chillclamp/rubyOnRails",
                        "stars": 0,
                        "img": "https://avatars.githubusercontent.com/u/133668746?s=40&v=4",
                        "owner": "Chillclamp",
                        "repo_name": "rubyOnRails"
                    },
                    {
                        "name": "DEFRA/flood-risk-back-office",
                        "stars": 2,
                        "img": "https://avatars.githubusercontent.com/u/5528822?s=40&v=4",
                        "owner": "DEFRA",
                        "repo_name": "flood-risk-back-office"
                    },
                    {
                        "name": "DEFRA/flood-risk-engine",
                        "stars": 3,
                        "img": "https://avatars.githubusercontent.com/u/5528822?s=40&v=4",
                        "owner": "DEFRA",
                        "repo_name": "flood-risk-engine"
                    },
                    {
                        "name": "DEFRA/flood-risk-front-office",
                        "stars": 2,
                        "img": "https://avatars.githubusercontent.com/u/5528822?s=40&v=4",
                        "owner": "DEFRA",
                        "repo_name": "flood-risk-front-office"
                    },
                    {
                        "name": "DEFRA/pafs-admin",
                        "stars": 0,
                        "img": "https://avatars.githubusercontent.com/u/5528822?s=40&v=4",
                        "owner": "DEFRA",
                        "repo_name": "pafs-admin"
                    },
                    {
                        "name": "DEFRA/pafs-user",
                        "stars": 2,
                        "img": "https://avatars.githubusercontent.com/u/5528822?s=40&v=4",
                        "owner": "DEFRA",
                        "repo_name": "pafs-user"
                    },
                    {
                        "name": "DEFRA/pafs_core",
                        "stars": 0,
                        "img": "https://avatars.githubusercontent.com/u/5528822?s=40&v=4",
                        "owner": "DEFRA",
                        "repo_name": "pafs_core"
                    },
                    {
                        "name": "DEFRA/waste-carriers-back-office",
                        "stars": 0,
                        "img": "https://avatars.githubusercontent.com/u/5528822?s=40&v=4",
                        "owner": "DEFRA",
                        "repo_name": "waste-carriers-back-office"
                    },
                    {
                        "name": "DEFRA/waste-carriers-engine",
                        "stars": 0,
                        "img": "https://avatars.githubusercontent.com/u/5528822?s=40&v=4",
                        "owner": "DEFRA",
                        "repo_name": "waste-carriers-engine"
                    },
                    {
                        "name": "DEFRA/waste-carriers-front-office",
                        "stars": 0,
                        "img": "https://avatars.githubusercontent.com/u/5528822?s=40&v=4",
                        "owner": "DEFRA",
                        "repo_name": "waste-carriers-front-office"
                    },
                    {
                        "name": "DFE-Digital/access-your-teaching-profile",
                        "stars": 0,
                        "img": "https://avatars.githubusercontent.com/u/30029772?s=40&v=4",
                        "owner": "DFE-Digital",
                        "repo_name": "access-your-teaching-profile"
                    },
                    {
                        "name": "DFE-Digital/access-your-teaching-qualifications",
                        "stars": 1,
                        "img": "https://avatars.githubusercontent.com/u/30029772?s=40&v=4",
                        "owner": "DFE-Digital",
                        "repo_name": "access-your-teaching-qualifications"
                    },
                    {
                        "name": "DFE-Digital/apply-for-qualified-teacher-status",
                        "stars": 6,
                        "img": "https://avatars.githubusercontent.com/u/30029772?s=40&v=4",
                        "owner": "DFE-Digital",
                        "repo_name": "apply-for-qualified-teacher-status"
                    },
                    {
                        "name": "DFE-Digital/apply-for-teacher-training",
                        "stars": 37,
                        "img": "https://avatars.githubusercontent.com/u/30029772?s=40&v=4",
                        "owner": "DFE-Digital",
                        "repo_name": "apply-for-teacher-training"
                    },
                    {
                        "name": "DFE-Digital/bat-ops-dashboard",
                        "stars": 0,
                        "img": "https://avatars.githubusercontent.com/u/30029772?s=40&v=4",
                        "owner": "DFE-Digital",
                        "repo_name": "bat-ops-dashboard"
                    },
                    {
                        "name": "DFE-Digital/buy-for-your-school",
                        "stars": 5,
                        "img": "https://avatars.githubusercontent.com/u/30029772?s=40&v=4",
                        "owner": "DFE-Digital",
                        "repo_name": "buy-for-your-school"
                    },
                    {
                        "name": "DFE-Digital/check-childrens-barred-list",
                        "stars": 2,
                        "img": "https://avatars.githubusercontent.com/u/30029772?s=40&v=4",
                        "owner": "DFE-Digital",
                        "repo_name": "check-childrens-barred-list"
                    },
                    {
                        "name": "DFE-Digital/childrens-social-care-placement",
                        "stars": 0,
                        "img": "https://avatars.githubusercontent.com/u/30029772?s=40&v=4",
                        "owner": "DFE-Digital",
                        "repo_name": "childrens-social-care-placement"
                    },
                    {
                        "name": "DFE-Digital/claim-additional-payments-for-teaching",
                        "stars": 14,
                        "img": "https://avatars.githubusercontent.com/u/30029772?s=40&v=4",
                        "owner": "DFE-Digital",
                        "repo_name": "claim-additional-payments-for-teaching"
                    },
                    {
                        "name": "DFE-Digital/csc-swr-prototype",
                        "stars": 0,
                        "img": "https://avatars.githubusercontent.com/u/30029772?s=40&v=4",
                        "owner": "DFE-Digital",
                        "repo_name": "csc-swr-prototype"
                    },
                    {
                        "name": "DFE-Digital/curriculum-materials",
                        "stars": 2,
                        "img": "https://avatars.githubusercontent.com/u/30029772?s=40&v=4",
                        "owner": "DFE-Digital",
                        "repo_name": "curriculum-materials"
                    },
                    {
                        "name": "DFE-Digital/data-allowances-prototype",
                        "stars": 0,
                        "img": "https://avatars.githubusercontent.com/u/30029772?s=40&v=4",
                        "owner": "DFE-Digital",
                        "repo_name": "data-allowances-prototype"
                    },
                    {
                        "name": "DFE-Digital/dfe-complete-conversions-transfers-and-changes",
                        "stars": 2,
                        "img": "https://avatars.githubusercontent.com/u/30029772?s=40&v=4",
                        "owner": "DFE-Digital",
                        "repo_name": "dfe-complete-conversions-transfers-and-changes"
                    },
                    {
                        "name": "DFE-Digital/early-careers-framework",
                        "stars": 8,
                        "img": "https://avatars.githubusercontent.com/u/30029772?s=40&v=4",
                        "owner": "DFE-Digital",
                        "repo_name": "early-careers-framework"
                    },
                    {
                        "name": "DFE-Digital/early-years-foundation-recovery",
                        "stars": 5,
                        "img": "https://avatars.githubusercontent.com/u/30029772?s=40&v=4",
                        "owner": "DFE-Digital",
                        "repo_name": "early-years-foundation-recovery"
                    },
                    {
                        "name": "DFE-Digital/early-years-foundation-reform",
                        "stars": 6,
                        "img": "https://avatars.githubusercontent.com/u/30029772?s=40&v=4",
                        "owner": "DFE-Digital",
                        "repo_name": "early-years-foundation-reform"
                    },
                    {
                        "name": "DFE-Digital/find-a-buying-solution",
                        "stars": 0,
                        "img": "https://avatars.githubusercontent.com/u/30029772?s=40&v=4",
                        "owner": "DFE-Digital",
                        "repo_name": "find-a-buying-solution"
                    },
                    {
                        "name": "DFE-Digital/find-a-lost-trn",
                        "stars": 4,
                        "img": "https://avatars.githubusercontent.com/u/30029772?s=40&v=4",
                        "owner": "DFE-Digital",
                        "repo_name": "find-a-lost-trn"
                    },
                    {
                        "name": "DFE-Digital/find-teacher-training",
                        "stars": 6,
                        "img": "https://avatars.githubusercontent.com/u/30029772?s=40&v=4",
                        "owner": "DFE-Digital",
                        "repo_name": "find-teacher-training"
                    },
                    {
                        "name": "DFE-Digital/formbuilder-demo",
                        "stars": 3,
                        "img": "https://avatars.githubusercontent.com/u/30029772?s=40&v=4",
                        "owner": "DFE-Digital",
                        "repo_name": "formbuilder-demo"
                    },
                    {
                        "name": "DFE-Digital/get-a-teacher-relocation-payment",
                        "stars": 0,
                        "img": "https://avatars.githubusercontent.com/u/30029772?s=40&v=4",
                        "owner": "DFE-Digital",
                        "repo_name": "get-a-teacher-relocation-payment"
                    },
                    {
                        "name": "DFE-Digital/get-help-with-remote-education",
                        "stars": 1,
                        "img": "https://avatars.githubusercontent.com/u/30029772?s=40&v=4",
                        "owner": "DFE-Digital",
                        "repo_name": "get-help-with-remote-education"
                    },
                    {
                        "name": "DFE-Digital/get-into-teaching-app",
                        "stars": 15,
                        "img": "https://avatars.githubusercontent.com/u/30029772?s=40&v=4",
                        "owner": "DFE-Digital",
                        "repo_name": "get-into-teaching-app"
                    },
                    {
                        "name": "DFE-Digital/govuk-rails-boilerplate",
                        "stars": 25,
                        "img": "https://avatars.githubusercontent.com/u/30029772?s=40&v=4",
                        "owner": "DFE-Digital",
                        "repo_name": "govuk-rails-boilerplate"
                    },
                    {
                        "name": "DFE-Digital/govuk-wizardry",
                        "stars": 5,
                        "img": "https://avatars.githubusercontent.com/u/30029772?s=40&v=4",
                        "owner": "DFE-Digital",
                        "repo_name": "govuk-wizardry"
                    },
                    {
                        "name": "DFE-Digital/govuk_feature_flags",
                        "stars": 4,
                        "img": "https://avatars.githubusercontent.com/u/30029772?s=40&v=4",
                        "owner": "DFE-Digital",
                        "repo_name": "govuk_feature_flags"
                    },
                    {
                        "name": "DFE-Digital/help-for-early-years-providers",
                        "stars": 0,
                        "img": "https://avatars.githubusercontent.com/u/30029772?s=40&v=4",
                        "owner": "DFE-Digital",
                        "repo_name": "help-for-early-years-providers"
                    },
                    {
                        "name": "DFE-Digital/itt-mentor-services",
                        "stars": 1,
                        "img": "https://avatars.githubusercontent.com/u/30029772?s=40&v=4",
                        "owner": "DFE-Digital",
                        "repo_name": "itt-mentor-services"
                    },
                    {
                        "name": "DFE-Digital/national-professional-qualification",
                        "stars": 0,
                        "img": "https://avatars.githubusercontent.com/u/30029772?s=40&v=4",
                        "owner": "DFE-Digital",
                        "repo_name": "national-professional-qualification"
                    },
                    {
                        "name": "DFE-Digital/npq-registration",
                        "stars": 5,
                        "img": "https://avatars.githubusercontent.com/u/30029772?s=40&v=4",
                        "owner": "DFE-Digital",
                        "repo_name": "npq-registration"
                    },
                    {
                        "name": "DFE-Digital/publish-teacher-training",
                        "stars": 9,
                        "img": "https://avatars.githubusercontent.com/u/30029772?s=40&v=4",
                        "owner": "DFE-Digital",
                        "repo_name": "publish-teacher-training"
                    },
                    {
                        "name": "DFE-Digital/publish-teacher-training-2022",
                        "stars": 5,
                        "img": "https://avatars.githubusercontent.com/u/30029772?s=40&v=4",
                        "owner": "DFE-Digital",
                        "repo_name": "publish-teacher-training-2022"
                    },
                    {
                        "name": "DFE-Digital/rails-7-boilerplate",
                        "stars": 1,
                        "img": "https://avatars.githubusercontent.com/u/30029772?s=40&v=4",
                        "owner": "DFE-Digital",
                        "repo_name": "rails-7-boilerplate"
                    },
                    {
                        "name": "DFE-Digital/refer-serious-misconduct",
                        "stars": 3,
                        "img": "https://avatars.githubusercontent.com/u/30029772?s=40&v=4",
                        "owner": "DFE-Digital",
                        "repo_name": "refer-serious-misconduct"
                    },
                    {
                        "name": "DFE-Digital/register-early-career-teachers-public",
                        "stars": 1,
                        "img": "https://avatars.githubusercontent.com/u/30029772?s=40&v=4",
                        "owner": "DFE-Digital",
                        "repo_name": "register-early-career-teachers-public"
                    },
                    {
                        "name": "DFE-Digital/register-trainee-teachers",
                        "stars": 11,
                        "img": "https://avatars.githubusercontent.com/u/30029772?s=40&v=4",
                        "owner": "DFE-Digital",
                        "repo_name": "register-trainee-teachers"
                    },
                    {
                        "name": "DFE-Digital/ruby-technical-test",
                        "stars": 0,
                        "img": "https://avatars.githubusercontent.com/u/30029772?s=40&v=4",
                        "owner": "DFE-Digital",
                        "repo_name": "ruby-technical-test"
                    },
                    {
                        "name": "DFE-Digital/schools-experience",
                        "stars": 9,
                        "img": "https://avatars.githubusercontent.com/u/30029772?s=40&v=4",
                        "owner": "DFE-Digital",
                        "repo_name": "schools-experience"
                    },
                    {
                        "name": "DFE-Digital/teacher-pay-calculator",
                        "stars": 0,
                        "img": "https://avatars.githubusercontent.com/u/30029772?s=40&v=4",
                        "owner": "DFE-Digital",
                        "repo_name": "teacher-pay-calculator"
                    },
                    {
                        "name": "DFE-Digital/teaching-school-hub-finder",
                        "stars": 1,
                        "img": "https://avatars.githubusercontent.com/u/30029772?s=40&v=4",
                        "owner": "DFE-Digital",
                        "repo_name": "teaching-school-hub-finder"
                    },
                    {
                        "name": "DFE-Digital/teaching-vacancies",
                        "stars": 23,
                        "img": "https://avatars.githubusercontent.com/u/30029772?s=40&v=4",
                        "owner": "DFE-Digital",
                        "repo_name": "teaching-vacancies"
                    },
                    {
                        "name": "FayeGoodworth/buy-for-your-school",
                        "stars": 0,
                        "img": "https://avatars.githubusercontent.com/u/62703351?s=40&v=4",
                        "owner": "FayeGoodworth",
                        "repo_name": "buy-for-your-school"
                    },
                    {
                        "name": "GovWifi/govwifi-admin",
                        "stars": 8,
                        "img": "https://avatars.githubusercontent.com/u/178180623?s=40&v=4",
                        "owner": "GovWifi",
                        "repo_name": "govwifi-admin"
                    },
                    {
                        "name": "Larisa-Romero/registro-docente",
                        "stars": 0,
                        "img": "https://avatars.githubusercontent.com/u/119458932?s=40&v=4",
                        "owner": "Larisa-Romero",
                        "repo_name": "registro-docente"
                    },
                    {
                        "name": "Lloyd-K/get-help-with-tech",
                        "stars": 0,
                        "img": "https://avatars.githubusercontent.com/u/68383886?s=40&v=4",
                        "owner": "Lloyd-K",
                        "repo_name": "get-help-with-tech"
                    },
                    {
                        "name": "OfficeForProductSafetyAndStandards/cosmetic-product-notifications",
                        "stars": 14,
                        "img": "https://avatars.githubusercontent.com/u/110820998?s=40&v=4",
                        "owner": "OfficeForProductSafetyAndStandards",
                        "repo_name": "cosmetic-product-notifications"
                    },
                    {
                        "name": "OfficeForProductSafetyAndStandards/product-safety-database",
                        "stars": 6,
                        "img": "https://avatars.githubusercontent.com/u/110820998?s=40&v=4",
                        "owner": "OfficeForProductSafetyAndStandards",
                        "repo_name": "product-safety-database"
                    },
                    {
                        "name": "UKGovernmentBEIS/beis-report-official-development-assistance",
                        "stars": 5,
                        "img": "https://avatars.githubusercontent.com/u/19221939?s=40&v=4",
                        "owner": "UKGovernmentBEIS",
                        "repo_name": "beis-report-official-development-assistance"
                    },
                    {
                        "name": "alphagov/forms-admin",
                        "stars": 17,
                        "img": "https://avatars.githubusercontent.com/u/596977?s=40&v=4",
                        "owner": "alphagov",
                        "repo_name": "forms-admin"
                    },
                    {
                        "name": "alphagov/forms-product-page",
                        "stars": 10,
                        "img": "https://avatars.githubusercontent.com/u/596977?s=40&v=4",
                        "owner": "alphagov",
                        "repo_name": "forms-product-page"
                    },
                    {
                        "name": "alphagov/forms-runner",
                        "stars": 9,
                        "img": "https://avatars.githubusercontent.com/u/596977?s=40&v=4",
                        "owner": "alphagov",
                        "repo_name": "forms-runner"
                    },
                    {
                        "name": "boost-entropy-ruby/govwifi-admin",
                        "stars": 0,
                        "img": "https://avatars.githubusercontent.com/u/83460344?s=40&v=4",
                        "owner": "boost-entropy-ruby",
                        "repo_name": "govwifi-admin"
                    },
                    {
                        "name": "cabinetoffice/fb-editor",
                        "stars": 0,
                        "img": "https://avatars.githubusercontent.com/u/5442909?s=40&v=4",
                        "owner": "cabinetoffice",
                        "repo_name": "fb-editor"
                    },
                    {
                        "name": "cabinetoffice/fb-metadata-api",
                        "stars": 0,
                        "img": "https://avatars.githubusercontent.com/u/5442909?s=40&v=4",
                        "owner": "cabinetoffice",
                        "repo_name": "fb-metadata-api"
                    },
                    {
                        "name": "cabinetoffice/fb-metadata-presenter",
                        "stars": 0,
                        "img": "https://avatars.githubusercontent.com/u/5442909?s=40&v=4",
                        "owner": "cabinetoffice",
                        "repo_name": "fb-metadata-presenter"
                    },
                    {
                        "name": "cabinetoffice/fb-runner",
                        "stars": 0,
                        "img": "https://avatars.githubusercontent.com/u/5442909?s=40&v=4",
                        "owner": "cabinetoffice",
                        "repo_name": "fb-runner"
                    },
                    {
                        "name": "cadmiumcat/forms-runner",
                        "stars": 0,
                        "img": "https://avatars.githubusercontent.com/u/52242161?s=40&v=4",
                        "owner": "cadmiumcat",
                        "repo_name": "forms-runner"
                    },
                    {
                        "name": "chris-groves/GDS-tasks",
                        "stars": 0,
                        "img": "https://avatars.githubusercontent.com/u/46629384?s=40&v=4",
                        "owner": "chris-groves",
                        "repo_name": "GDS-tasks"
                    },
                    {
                        "name": "chris-groves/rock-paper-scissors",
                        "stars": 0,
                        "img": "https://avatars.githubusercontent.com/u/46629384?s=40&v=4",
                        "owner": "chris-groves",
                        "repo_name": "rock-paper-scissors"
                    },
                    {
                        "name": "cmagovuk/oim-report-an-issue-app",
                        "stars": 0,
                        "img": "https://avatars.githubusercontent.com/u/49915532?s=40&v=4",
                        "owner": "cmagovuk",
                        "repo_name": "oim-report-an-issue-app"
                    },
                    {
                        "name": "cmagovuk/public-access-gateway-app",
                        "stars": 1,
                        "img": "https://avatars.githubusercontent.com/u/49915532?s=40&v=4",
                        "owner": "cmagovuk",
                        "repo_name": "public-access-gateway-app"
                    },
                    {
                        "name": "cmagovuk/sau-pa-portal",
                        "stars": 0,
                        "img": "https://avatars.githubusercontent.com/u/49915532?s=40&v=4",
                        "owner": "cmagovuk",
                        "repo_name": "sau-pa-portal"
                    },
                    {
                        "name": "cmagovuk/whistleblower",
                        "stars": 0,
                        "img": "https://avatars.githubusercontent.com/u/49915532?s=40&v=4",
                        "owner": "cmagovuk",
                        "repo_name": "whistleblower"
                    },
                    {
                        "name": "co-cddo/dea-register-frontend",
                        "stars": 0,
                        "img": "https://avatars.githubusercontent.com/u/94975489?s=40&v=4",
                        "owner": "co-cddo",
                        "repo_name": "dea-register-frontend"
                    },
                    {
                        "name": "co-cddo/dm-client-demo",
                        "stars": 0,
                        "img": "https://avatars.githubusercontent.com/u/94975489?s=40&v=4",
                        "owner": "co-cddo",
                        "repo_name": "dm-client-demo"
                    },
                    {
                        "name": "co-cddo/esda-builder",
                        "stars": 0,
                        "img": "https://avatars.githubusercontent.com/u/94975489?s=40&v=4",
                        "owner": "co-cddo",
                        "repo_name": "esda-builder"
                    },
                    {
                        "name": "communitiesuk/submit-social-housing-lettings-and-sales-data",
                        "stars": 6,
                        "img": "https://avatars.githubusercontent.com/u/12797589?s=40&v=4",
                        "owner": "communitiesuk",
                        "repo_name": "submit-social-housing-lettings-and-sales-data"
                    },
                    {
                        "name": "communitiesuk/ukraine-sponsor-resettlement",
                        "stars": 6,
                        "img": "https://avatars.githubusercontent.com/u/12797589?s=40&v=4",
                        "owner": "communitiesuk",
                        "repo_name": "ukraine-sponsor-resettlement"
                    },
                    {
                        "name": "design-history/design-history",
                        "stars": 10,
                        "img": "https://avatars.githubusercontent.com/u/86117238?s=40&v=4",
                        "owner": "design-history",
                        "repo_name": "design-history"
                    },
                    {
                        "name": "dsp-testing/apply-for-teacher-training",
                        "stars": 0,
                        "img": "https://avatars.githubusercontent.com/u/30846345?s=40&v=4",
                        "owner": "dsp-testing",
                        "repo_name": "apply-for-teacher-training"
                    },
                    {
                        "name": "dxw/dfsseta-apply-for-landing-ruby",
                        "stars": 1,
                        "img": "https://avatars.githubusercontent.com/u/27897?s=40&v=4",
                        "owner": "dxw",
                        "repo_name": "dfsseta-apply-for-landing-ruby"
                    },
                    {
                        "name": "ebrett/rails7example",
                        "stars": 1,
                        "img": "https://avatars.githubusercontent.com/u/6605?s=40&v=4",
                        "owner": "ebrett",
                        "repo_name": "rails7example"
                    },
                    {
                        "name": "fumimowdan/irp_policy",
                        "stars": 0,
                        "img": "https://avatars.githubusercontent.com/u/139925286?s=40&v=4",
                        "owner": "fumimowdan",
                        "repo_name": "irp_policy"
                    },
                    {
                        "name": "gpeng/dfe-code-test",
                        "stars": 0,
                        "img": "https://avatars.githubusercontent.com/u/5216?s=40&v=4",
                        "owner": "gpeng",
                        "repo_name": "dfe-code-test"
                    },
                    {
                        "name": "graphia/wizardry-demo",
                        "stars": 0,
                        "img": "https://avatars.githubusercontent.com/u/25978684?s=40&v=4",
                        "owner": "graphia",
                        "repo_name": "wizardry-demo"
                    },
                    {
                        "name": "graphia/wizardry-sample-app",
                        "stars": 0,
                        "img": "https://avatars.githubusercontent.com/u/25978684?s=40&v=4",
                        "owner": "graphia",
                        "repo_name": "wizardry-sample-app"
                    },
                    {
                        "name": "hmcts/c100-application",
                        "stars": 0,
                        "img": "https://avatars.githubusercontent.com/u/22817111?s=40&v=4",
                        "owner": "hmcts",
                        "repo_name": "c100-application"
                    },
                    {
                        "name": "hmcts/et-pet-et1",
                        "stars": 9,
                        "img": "https://avatars.githubusercontent.com/u/22817111?s=40&v=4",
                        "owner": "hmcts",
                        "repo_name": "et-pet-et1"
                    },
                    {
                        "name": "hmcts/et-pet-et3",
                        "stars": 2,
                        "img": "https://avatars.githubusercontent.com/u/22817111?s=40&v=4",
                        "owner": "hmcts",
                        "repo_name": "et-pet-et3"
                    },
                    {
                        "name": "hmcts/et_gds_design_system",
                        "stars": 0,
                        "img": "https://avatars.githubusercontent.com/u/22817111?s=40&v=4",
                        "owner": "hmcts",
                        "repo_name": "et_gds_design_system"
                    },
                    {
                        "name": "hmcts/tax-tribunals-datacapture",
                        "stars": 0,
                        "img": "https://avatars.githubusercontent.com/u/22817111?s=40&v=4",
                        "owner": "hmcts",
                        "repo_name": "tax-tribunals-datacapture"
                    },
                    {
                        "name": "jrmhaig/govuk_formbuilder_test",
                        "stars": 0,
                        "img": "https://avatars.githubusercontent.com/u/4415912?s=40&v=4",
                        "owner": "jrmhaig",
                        "repo_name": "govuk_formbuilder_test"
                    },
                    {
                        "name": "katalyst/govuk-formbuilder",
                        "stars": 3,
                        "img": "https://avatars.githubusercontent.com/u/15221?s=40&v=4",
                        "owner": "katalyst",
                        "repo_name": "govuk-formbuilder"
                    },
                    {
                        "name": "katalyst/koi",
                        "stars": 9,
                        "img": "https://avatars.githubusercontent.com/u/15221?s=40&v=4",
                        "owner": "katalyst",
                        "repo_name": "koi"
                    },
                    {
                        "name": "ministryofjustice/Claim-for-Crown-Court-Defence",
                        "stars": 25,
                        "img": "https://avatars.githubusercontent.com/u/2203574?s=40&v=4",
                        "owner": "ministryofjustice",
                        "repo_name": "Claim-for-Crown-Court-Defence"
                    },
                    {
                        "name": "ministryofjustice/c100-application",
                        "stars": 0,
                        "img": "https://avatars.githubusercontent.com/u/2203574?s=40&v=4",
                        "owner": "ministryofjustice",
                        "repo_name": "c100-application"
                    },
                    {
                        "name": "ministryofjustice/cdpt-deploys-dashboard",
                        "stars": 0,
                        "img": "https://avatars.githubusercontent.com/u/2203574?s=40&v=4",
                        "owner": "ministryofjustice",
                        "repo_name": "cdpt-deploys-dashboard"
                    },
                    {
                        "name": "ministryofjustice/correspondence_tool_public",
                        "stars": 3,
                        "img": "https://avatars.githubusercontent.com/u/2203574?s=40&v=4",
                        "owner": "ministryofjustice",
                        "repo_name": "correspondence_tool_public"
                    },
                    {
                        "name": "ministryofjustice/disclosure-checker",
                        "stars": 0,
                        "img": "https://avatars.githubusercontent.com/u/2203574?s=40&v=4",
                        "owner": "ministryofjustice",
                        "repo_name": "disclosure-checker"
                    },
                    {
                        "name": "ministryofjustice/fb-editor",
                        "stars": 0,
                        "img": "https://avatars.githubusercontent.com/u/2203574?s=40&v=4",
                        "owner": "ministryofjustice",
                        "repo_name": "fb-editor"
                    },
                    {
                        "name": "ministryofjustice/fb-metadata-api",
                        "stars": 0,
                        "img": "https://avatars.githubusercontent.com/u/2203574?s=40&v=4",
                        "owner": "ministryofjustice",
                        "repo_name": "fb-metadata-api"
                    },
                    {
                        "name": "ministryofjustice/fb-metadata-presenter",
                        "stars": 1,
                        "img": "https://avatars.githubusercontent.com/u/2203574?s=40&v=4",
                        "owner": "ministryofjustice",
                        "repo_name": "fb-metadata-presenter"
                    },
                    {
                        "name": "ministryofjustice/fb-runner",
                        "stars": 1,
                        "img": "https://avatars.githubusercontent.com/u/2203574?s=40&v=4",
                        "owner": "ministryofjustice",
                        "repo_name": "fb-runner"
                    },
                    {
                        "name": "ministryofjustice/find-unclaimed-court-money",
                        "stars": 0,
                        "img": "https://avatars.githubusercontent.com/u/2203574?s=40&v=4",
                        "owner": "ministryofjustice",
                        "repo_name": "find-unclaimed-court-money"
                    },
                    {
                        "name": "ministryofjustice/help-with-child-arrangements",
                        "stars": 0,
                        "img": "https://avatars.githubusercontent.com/u/2203574?s=40&v=4",
                        "owner": "ministryofjustice",
                        "repo_name": "help-with-child-arrangements"
                    },
                    {
                        "name": "ministryofjustice/laa-apply-for-criminal-legal-aid",
                        "stars": 4,
                        "img": "https://avatars.githubusercontent.com/u/2203574?s=40&v=4",
                        "owner": "ministryofjustice",
                        "repo_name": "laa-apply-for-criminal-legal-aid"
                    },
                    {
                        "name": "ministryofjustice/laa-apply-for-legal-aid",
                        "stars": 17,
                        "img": "https://avatars.githubusercontent.com/u/2203574?s=40&v=4",
                        "owner": "ministryofjustice",
                        "repo_name": "laa-apply-for-legal-aid"
                    },
                    {
                        "name": "ministryofjustice/laa-assess-crime-forms",
                        "stars": 0,
                        "img": "https://avatars.githubusercontent.com/u/2203574?s=40&v=4",
                        "owner": "ministryofjustice",
                        "repo_name": "laa-assess-crime-forms"
                    },
                    {
                        "name": "ministryofjustice/laa-assure-hmrc-data",
                        "stars": 1,
                        "img": "https://avatars.githubusercontent.com/u/2203574?s=40&v=4",
                        "owner": "ministryofjustice",
                        "repo_name": "laa-assure-hmrc-data"
                    },
                    {
                        "name": "ministryofjustice/laa-check-client-qualifies",
                        "stars": 5,
                        "img": "https://avatars.githubusercontent.com/u/2203574?s=40&v=4",
                        "owner": "ministryofjustice",
                        "repo_name": "laa-check-client-qualifies"
                    },
                    {
                        "name": "ministryofjustice/laa-court-data-ui",
                        "stars": 7,
                        "img": "https://avatars.githubusercontent.com/u/2203574?s=40&v=4",
                        "owner": "ministryofjustice",
                        "repo_name": "laa-court-data-ui"
                    },
                    {
                        "name": "ministryofjustice/laa-fee-calculator-user-interface",
                        "stars": 2,
                        "img": "https://avatars.githubusercontent.com/u/2203574?s=40&v=4",
                        "owner": "ministryofjustice",
                        "repo_name": "laa-fee-calculator-user-interface"
                    },
                    {
                        "name": "ministryofjustice/laa-review-criminal-legal-aid",
                        "stars": 3,
                        "img": "https://avatars.githubusercontent.com/u/2203574?s=40&v=4",
                        "owner": "ministryofjustice",
                        "repo_name": "laa-review-criminal-legal-aid"
                    },
                    {
                        "name": "ministryofjustice/laa-submit-crime-forms",
                        "stars": 2,
                        "img": "https://avatars.githubusercontent.com/u/2203574?s=40&v=4",
                        "owner": "ministryofjustice",
                        "repo_name": "laa-submit-crime-forms"
                    },
                    {
                        "name": "ministryofjustice/offender-management-allocation-manager",
                        "stars": 7,
                        "img": "https://avatars.githubusercontent.com/u/2203574?s=40&v=4",
                        "owner": "ministryofjustice",
                        "repo_name": "offender-management-allocation-manager"
                    },
                    {
                        "name": "ministryofjustice/request-personal-information",
                        "stars": 0,
                        "img": "https://avatars.githubusercontent.com/u/2203574?s=40&v=4",
                        "owner": "ministryofjustice",
                        "repo_name": "request-personal-information"
                    },
                    {
                        "name": "ministryofjustice/tax-tribunals-datacapture",
                        "stars": 3,
                        "img": "https://avatars.githubusercontent.com/u/2203574?s=40&v=4",
                        "owner": "ministryofjustice",
                        "repo_name": "tax-tribunals-datacapture"
                    },
                    {
                        "name": "moda-gov-tw/alphagov.forms-admin",
                        "stars": 3,
                        "img": "https://avatars.githubusercontent.com/u/107838243?s=40&v=4",
                        "owner": "moda-gov-tw",
                        "repo_name": "alphagov.forms-admin"
                    },
                    {
                        "name": "moda-gov-tw/alphagov.forms-runner",
                        "stars": 1,
                        "img": "https://avatars.githubusercontent.com/u/107838243?s=40&v=4",
                        "owner": "moda-gov-tw",
                        "repo_name": "alphagov.forms-runner"
                    },
                    {
                        "name": "nareshdevasani/all_ruby_deps",
                        "stars": 0,
                        "img": "https://avatars.githubusercontent.com/u/22427191?s=40&v=4",
                        "owner": "nareshdevasani",
                        "repo_name": "all_ruby_deps"
                    },
                    {
                        "name": "nhsuk/manage-vaccinations-in-schools",
                        "stars": 8,
                        "img": "https://avatars.githubusercontent.com/u/18658529?s=40&v=4",
                        "owner": "nhsuk",
                        "repo_name": "manage-vaccinations-in-schools"
                    },
                    {
                        "name": "quietsoph/vocab-builder-app",
                        "stars": 1,
                        "img": "https://avatars.githubusercontent.com/u/101964205?s=40&v=4",
                        "owner": "quietsoph",
                        "repo_name": "vocab-builder-app"
                    },
                    {
                        "name": "rowlando/apply-for-la",
                        "stars": 0,
                        "img": "https://avatars.githubusercontent.com/u/89347?s=40&v=4",
                        "owner": "rowlando",
                        "repo_name": "apply-for-la"
                    },
                    {
                        "name": "stellenberger/rails_multi_step",
                        "stars": 1,
                        "img": "https://avatars.githubusercontent.com/u/53180713?s=40&v=4",
                        "owner": "stellenberger",
                        "repo_name": "rails_multi_step"
                    },
                    {
                        "name": "trade-tariff/trade-tariff-admin",
                        "stars": 1,
                        "img": "https://avatars.githubusercontent.com/u/79591050?s=40&v=4",
                        "owner": "trade-tariff",
                        "repo_name": "trade-tariff-admin"
                    },
                    {
                        "name": "trade-tariff/trade-tariff-duty-calculator",
                        "stars": 2,
                        "img": "https://avatars.githubusercontent.com/u/79591050?s=40&v=4",
                        "owner": "trade-tariff",
                        "repo_name": "trade-tariff-duty-calculator"
                    },
                    {
                        "name": "trade-tariff/trade-tariff-frontend",
                        "stars": 2,
                        "img": "https://avatars.githubusercontent.com/u/79591050?s=40&v=4",
                        "owner": "trade-tariff",
                        "repo_name": "trade-tariff-frontend"
                    },
                    {
                        "name": "tvararu/govuk-mockup-kit",
                        "stars": 1,
                        "img": "https://avatars.githubusercontent.com/u/1650875?s=40&v=4",
                        "owner": "tvararu",
                        "repo_name": "govuk-mockup-kit"
                    },
                    {
                        "name": "tvararu/ravn",
                        "stars": 0,
                        "img": "https://avatars.githubusercontent.com/u/1650875?s=40&v=4",
                        "owner": "tvararu",
                        "repo_name": "ravn"
                    },
                    {
                        "name": "unboxed/bops",
                        "stars": 12,
                        "img": "https://avatars.githubusercontent.com/u/47633?s=40&v=4",
                        "owner": "unboxed",
                        "repo_name": "bops"
                    },
                    {
                        "name": "unboxed/bops-applicants",
                        "stars": 1,
                        "img": "https://avatars.githubusercontent.com/u/47633?s=40&v=4",
                        "owner": "unboxed",
                        "repo_name": "bops-applicants"
                    },
                    {
                        "name": "your/status-dashboard",
                        "stars": 0,
                        "img": "https://avatars.githubusercontent.com/u/9043263?s=40&v=4",
                        "owner": "your",
                        "repo_name": "status-dashboard"
                    }
                ],
                "public_dependents_number": 133,
                "private_dependents_number": -133,
                "total_dependents_number": 133,
                "badges": {
                    "total": "[![Generated by github-dependents-info](https://img.shields.io/static/v1?label=Used%20by&message=133&color=informational&logo=slickpic)](https://github.com/x-govuk/govuk-form-builder/network/dependents)",
                    "public": "[![Generated by github-dependents-info](https://img.shields.io/static/v1?label=Used%20by%20(public)&message=133&color=informational&logo=slickpic)](https://github.com/x-govuk/govuk-form-builder/network/dependents)",
                    "private": "[![Generated by github-dependents-info](https://img.shields.io/static/v1?label=Used%20by%20(private)&message=-133&color=informational&logo=slickpic)](https://github.com/x-govuk/govuk-form-builder/network/dependents)",
                    "stars": "[![Generated by github-dependents-info](https://img.shields.io/static/v1?label=Used%20by%20(stars)&message=123&color=informational&logo=slickpic)](https://github.com/x-govuk/govuk-form-builder/network/dependents)"
                }
            }
        ]
    ]
}
